{
    "teams": [
        {
            "idTeam": "144590",
            "idESPN": null,
            "idAPIfootball": "2563",
            "intLoved": null,
            "strTeam": "Beijing Great Wall",
            "strTeamAlternate": "",
            "strTeamShort": null,
            "intFormedYear": "2002",
            "strSport": "Basketball",
            "strLeague": "Chinese WCBA",
            "idLeague": "5131",
            "strLeague2": "",
            "idLeague2": null,
            "strLeague3": "",
            "idLeague3": null,
            "strLeague4": "",
            "idLeague4": null,
            "strLeague5": "",
            "idLeague5": null,
            "strLeague6": "",
            "idLeague6": null,
            "strLeague7": "",
            "idLeague7": null,
            "strDivision": null,
            "idVenue": null,
            "strStadium": "Shougang Gymnasium",
            "strKeywords": "",
            "strRSS": "",
            "strLocation": "Beijing",
            "intStadiumCapacity": "6000",
            "strWebsite": "",
            "strFacebook": "",
            "strTwitter": "",
            "strInstagram": "",
            "strDescriptionEN": "Beijing Great Wall is a Chinese professional women's basketball club based in Beijing, playing in the Women's Chinese Basketball Association (WCBA). The team is owned by Beijing Shougang Co., Ltd., which also owns the Beijing Ducks men's basketball team. Beijing Great Wall sometimes also carries the name of its sponsor BBMG.\r\n\r\nThe team won 4 WCBA championships, first in 2012 and more recently from 2016 to 2018.",
            "strDescriptionDE": null,
            "strDescriptionFR": null,
            "strDescriptionCN": null,
            "strDescriptionIT": null,
            "strDescriptionJP": null,
            "strDescriptionRU": null,
            "strDescriptionES": null,
            "strDescriptionPT": null,
            "strDescriptionSE": null,
            "strDescriptionNL": null,
            "strDescriptionHU": null,
            "strDescriptionNO": null,
            "strDescriptionIL": null,
            "strDescriptionPL": null,
            "strColour1": null,
            "strColour2": null,
            "strColour3": null,
            "strGender": "Female",
            "strCountry": "China",
            "strBadge": "https:\/\/r2.thesportsdb.com\/images\/media\/team\/badge\/djvqlb1638031905.png",
            "strLogo": null,
            "strFanart1": null,
            "strFanart2": null,
            "strFanart3": null,
            "strFanart4": null,
            "strBanner": null,
            "strEquipment": null,
            "strYoutube": "",
            "strLocked": "unlocked"
        },
        {
            "idTeam": "148322",
            "idESPN": null,
            "idAPIfootball": "6268",
            "intLoved": null,
            "strTeam": "Daqing Women",
            "strTeamAlternate": "",
            "strTeamShort": "",
            "intFormedYear": "0",
            "strSport": "Basketball",
            "strLeague": "Chinese WCBA",
            "idLeague": "5131",
            "strLeague2": "",
            "idLeague2": null,
            "strLeague3": "",
            "idLeague3": null,
            "strLeague4": "",
            "idLeague4": null,
            "strLeague5": "",
            "idLeague5": null,
            "strLeague6": "",
            "idLeague6": null,
            "strLeague7": "",
            "idLeague7": null,
            "strDivision": null,
            "idVenue": null,
            "strStadium": "",
            "strKeywords": "",
            "strRSS": "",
            "strLocation": "",
            "intStadiumCapacity": "0",
            "strWebsite": "",
            "strFacebook": "",
            "strTwitter": "",
            "strInstagram": "",
            "strDescriptionEN": "Heilongjiang Dragons (Chinese: 华龙女篮; pinyin: Huálóng Nǚlán) is a Chinese professional women's basketball club based in Daqing, Heilongjiang, playing in the Women's Chinese Basketball Association (WCBA).\r\n\r\nCreated by Jiang Zuozhi in the 1990s, it is the oldest Women's Basketball team in China.\r\n\r\nThe club has formed several important players, including Miao Lijie, Ma Zongqing, Liu Yutong, and others.",
            "strDescriptionDE": null,
            "strDescriptionFR": null,
            "strDescriptionCN": null,
            "strDescriptionIT": null,
            "strDescriptionJP": null,
            "strDescriptionRU": null,
            "strDescriptionES": null,
            "strDescriptionPT": null,
            "strDescriptionSE": null,
            "strDescriptionNL": null,
            "strDescriptionHU": null,
            "strDescriptionNO": null,
            "strDescriptionIL": null,
            "strDescriptionPL": null,
            "strColour1": "",
            "strColour2": "",
            "strColour3": "",
            "strGender": "Male",
            "strCountry": "China",
            "strBadge": "https:\/\/r2.thesportsdb.com\/images\/media\/team\/badge\/pe6q991714043583.png",
            "strLogo": null,
            "strFanart1": null,
            "strFanart2": null,
            "strFanart3": null,
            "strFanart4": null,
            "strBanner": null,
            "strEquipment": null,
            "strYoutube": "",
            "strLocked": "unlocked"
        },
        {
            "idTeam": "144926",
            "idESPN": null,
            "idAPIfootball": "2564",
            "intLoved": null,
            "strTeam": "Fujian Zoten",
            "strTeamAlternate": "",
            "strTeamShort": null,
            "intFormedYear": "0",
            "strSport": "Basketball",
            "strLeague": "Chinese WCBA",
            "idLeague": "5131",
            "strLeague2": "",
            "idLeague2": null,
            "strLeague3": "",
            "idLeague3": null,
            "strLeague4": "",
            "idLeague4": null,
            "strLeague5": "",
            "idLeague5": null,
            "strLeague6": "",
            "idLeague6": null,
            "strLeague7": "",
            "idLeague7": null,
            "strDivision": null,
            "idVenue": null,
            "strStadium": "",
            "strKeywords": "",
            "strRSS": "",
            "strLocation": "",
            "intStadiumCapacity": "0",
            "strWebsite": "",
            "strFacebook": "",
            "strTwitter": "",
            "strInstagram": "",
            "strDescriptionEN": null,
            "strDescriptionDE": null,
            "strDescriptionFR": null,
            "strDescriptionCN": null,
            "strDescriptionIT": null,
            "strDescriptionJP": null,
            "strDescriptionRU": null,
            "strDescriptionES": null,
            "strDescriptionPT": null,
            "strDescriptionSE": null,
            "strDescriptionNL": null,
            "strDescriptionHU": null,
            "strDescriptionNO": null,
            "strDescriptionIL": null,
            "strDescriptionPL": null,
            "strColour1": null,
            "strColour2": null,
            "strColour3": null,
            "strGender": "Male",
            "strCountry": "China",
            "strBadge": "https:\/\/r2.thesportsdb.com\/images\/media\/team\/badge\/bbyrjk1704740734.png",
            "strLogo": null,
            "strFanart1": null,
            "strFanart2": null,
            "strFanart3": null,
            "strFanart4": null,
            "strBanner": null,
            "strEquipment": null,
            "strYoutube": "",
            "strLocked": "unlocked"
        },
        {
            "idTeam": "144927",
            "idESPN": null,
            "idAPIfootball": "3377",
            "intLoved": null,
            "strTeam": "FUSC Women",
            "strTeamAlternate": "",
            "strTeamShort": null,
            "intFormedYear": "0",
            "strSport": "Basketball",
            "strLeague": "Chinese WCBA",
            "idLeague": "5131",
            "strLeague2": "",
            "idLeague2": null,
            "strLeague3": "",
            "idLeague3": null,
            "strLeague4": "",
            "idLeague4": null,
            "strLeague5": "",
            "idLeague5": null,
            "strLeague6": "",
            "idLeague6": null,
            "strLeague7": "",
            "idLeague7": null,
            "strDivision": null,
            "idVenue": null,
            "strStadium": "",
            "strKeywords": "",
            "strRSS": "",
            "strLocation": "",
            "intStadiumCapacity": "0",
            "strWebsite": "",
            "strFacebook": "",
            "strTwitter": "",
            "strInstagram": "",
            "strDescriptionEN": null,
            "strDescriptionDE": null,
            "strDescriptionFR": null,
            "strDescriptionCN": null,
            "strDescriptionIT": null,
            "strDescriptionJP": null,
            "strDescriptionRU": null,
            "strDescriptionES": null,
            "strDescriptionPT": null,
            "strDescriptionSE": null,
            "strDescriptionNL": null,
            "strDescriptionHU": null,
            "strDescriptionNO": null,
            "strDescriptionIL": null,
            "strDescriptionPL": null,
            "strColour1": null,
            "strColour2": null,
            "strColour3": null,
            "strGender": "Male",
            "strCountry": "China",
            "strBadge": "https:\/\/r2.thesportsdb.com\/images\/media\/team\/badge\/aupzky1704741563.png",
            "strLogo": null,
            "strFanart1": null,
            "strFanart2": null,
            "strFanart3": null,
            "strFanart4": null,
            "strBanner": null,
            "strEquipment": null,
            "strYoutube": "",
            "strLocked": "unlocked"
        },
        {
            "idTeam": "144591",
            "idESPN": null,
            "idAPIfootball": "2565",
            "intLoved": null,
            "strTeam": "Guangdong Vermilion Birds",
            "strTeamAlternate": "",
            "strTeamShort": null,
            "intFormedYear": "2002",
            "strSport": "Basketball",
            "strLeague": "Chinese WCBA",
            "idLeague": "5131",
            "strLeague2": "",
            "idLeague2": null,
            "strLeague3": "",
            "idLeague3": null,
            "strLeague4": "",
            "idLeague4": null,
            "strLeague5": "",
            "idLeague5": null,
            "strLeague6": "",
            "idLeague6": null,
            "strLeague7": "",
            "idLeague7": null,
            "strDivision": null,
            "idVenue": null,
            "strStadium": "Dalang Arena",
            "strKeywords": "",
            "strRSS": "",
            "strLocation": "Dongguan",
            "intStadiumCapacity": "4000",
            "strWebsite": "",
            "strFacebook": "",
            "strTwitter": "",
            "strInstagram": "",
            "strDescriptionEN": "Guangdong Vermilion Birds is a Chinese professional women's basketball club based in Dongguan, Guangdong, playing in the Women's Chinese Basketball Association (WCBA). It was known as Guangdong Dolphins from 2007–2018 and Guangdong Kapok before 2007.\r\n\r\nThe Vermilion Bird is a mythical creature in Chinese culture.",
            "strDescriptionDE": null,
            "strDescriptionFR": null,
            "strDescriptionCN": null,
            "strDescriptionIT": null,
            "strDescriptionJP": null,
            "strDescriptionRU": null,
            "strDescriptionES": null,
            "strDescriptionPT": null,
            "strDescriptionSE": null,
            "strDescriptionNL": null,
            "strDescriptionHU": null,
            "strDescriptionNO": null,
            "strDescriptionIL": null,
            "strDescriptionPL": null,
            "strColour1": null,
            "strColour2": null,
            "strColour3": null,
            "strGender": "Female",
            "strCountry": "China",
            "strBadge": "https:\/\/r2.thesportsdb.com\/images\/media\/team\/badge\/89odlp1704744265.png",
            "strLogo": null,
            "strFanart1": null,
            "strFanart2": null,
            "strFanart3": null,
            "strFanart4": null,
            "strBanner": null,
            "strEquipment": null,
            "strYoutube": "",
            "strLocked": "unlocked"
        },
        {
            "idTeam": "144592",
            "idESPN": null,
            "idAPIfootball": "2566",
            "intLoved": null,
            "strTeam": "Hebei Win Power",
            "strTeamAlternate": "",
            "strTeamShort": null,
            "intFormedYear": "2018",
            "strSport": "Basketball",
            "strLeague": "Chinese WCBA",
            "idLeague": "5131",
            "strLeague2": "",
            "idLeague2": null,
            "strLeague3": "",
            "idLeague3": null,
            "strLeague4": "",
            "idLeague4": null,
            "strLeague5": "",
            "idLeague5": null,
            "strLeague6": "",
            "idLeague6": null,
            "strLeague7": "",
            "idLeague7": null,
            "strDivision": null,
            "idVenue": null,
            "strStadium": "Hengshui Stadium",
            "strKeywords": "",
            "strRSS": "",
            "strLocation": "Hengshui",
            "intStadiumCapacity": "3600",
            "strWebsite": "",
            "strFacebook": "",
            "strTwitter": "",
            "strInstagram": "",
            "strDescriptionEN": "Hebei Win Power is a Chinese professional women's basketball club in the Women's Chinese Basketball Association (WCBA), based in Hengshui, Hebei.",
            "strDescriptionDE": null,
            "strDescriptionFR": null,
            "strDescriptionCN": null,
            "strDescriptionIT": null,
            "strDescriptionJP": null,
            "strDescriptionRU": null,
            "strDescriptionES": null,
            "strDescriptionPT": null,
            "strDescriptionSE": null,
            "strDescriptionNL": null,
            "strDescriptionHU": null,
            "strDescriptionNO": null,
            "strDescriptionIL": null,
            "strDescriptionPL": null,
            "strColour1": null,
            "strColour2": null,
            "strColour3": null,
            "strGender": "Female",
            "strCountry": "China",
            "strBadge": "https:\/\/r2.thesportsdb.com\/images\/media\/team\/badge\/3ksj481638031914.png",
            "strLogo": null,
            "strFanart1": null,
            "strFanart2": null,
            "strFanart3": null,
            "strFanart4": null,
            "strBanner": null,
            "strEquipment": null,
            "strYoutube": "",
            "strLocked": "unlocked"
        },
        {
            "idTeam": "144593",
            "idESPN": null,
            "idAPIfootball": "2567",
            "intLoved": null,
            "strTeam": "Heilongjiang Dragons",
            "strTeamAlternate": "",
            "strTeamShort": null,
            "intFormedYear": "2002",
            "strSport": "Basketball",
            "strLeague": "Chinese WCBA",
            "idLeague": "5131",
            "strLeague2": "",
            "idLeague2": null,
            "strLeague3": "",
            "idLeague3": null,
            "strLeague4": "",
            "idLeague4": null,
            "strLeague5": "",
            "idLeague5": null,
            "strLeague6": "",
            "idLeague6": null,
            "strLeague7": "",
            "idLeague7": null,
            "strDivision": null,
            "idVenue": null,
            "strStadium": "Daqing Stadium",
            "strKeywords": "",
            "strRSS": "",
            "strLocation": "Daqing",
            "intStadiumCapacity": "0",
            "strWebsite": "",
            "strFacebook": "",
            "strTwitter": "",
            "strInstagram": "",
            "strDescriptionEN": "Heilongjiang Dragons (华龙女篮) is a Chinese professional women's basketball club based in Daqing, Heilongjiang, playing in the Women's Chinese Basketball Association (WCBA).",
            "strDescriptionDE": null,
            "strDescriptionFR": null,
            "strDescriptionCN": null,
            "strDescriptionIT": null,
            "strDescriptionJP": null,
            "strDescriptionRU": null,
            "strDescriptionES": null,
            "strDescriptionPT": null,
            "strDescriptionSE": null,
            "strDescriptionNL": null,
            "strDescriptionHU": null,
            "strDescriptionNO": null,
            "strDescriptionIL": null,
            "strDescriptionPL": null,
            "strColour1": null,
            "strColour2": null,
            "strColour3": null,
            "strGender": "Female",
            "strCountry": "China",
            "strBadge": "https:\/\/r2.thesportsdb.com\/images\/media\/team\/badge\/c9jm821704744756.png",
            "strLogo": null,
            "strFanart1": null,
            "strFanart2": null,
            "strFanart3": null,
            "strFanart4": null,
            "strBanner": null,
            "strEquipment": null,
            "strYoutube": "",
            "strLocked": "unlocked"
        },
        {
            "idTeam": "148321",
            "idESPN": null,
            "idAPIfootball": "2568",
            "intLoved": null,
            "strTeam": "Henan Women",
            "strTeamAlternate": "",
            "strTeamShort": "",
            "intFormedYear": "2002",
            "strSport": "Basketball",
            "strLeague": "Chinese WCBA",
            "idLeague": "5131",
            "strLeague2": "",
            "idLeague2": null,
            "strLeague3": "",
            "idLeague3": null,
            "strLeague4": "",
            "idLeague4": null,
            "strLeague5": "",
            "idLeague5": null,
            "strLeague6": "",
            "idLeague6": null,
            "strLeague7": "",
            "idLeague7": null,
            "strDivision": null,
            "idVenue": null,
            "strStadium": "Luoyang Stadium",
            "strKeywords": "",
            "strRSS": "",
            "strLocation": "Luoyang, Henan",
            "intStadiumCapacity": "6000",
            "strWebsite": "",
            "strFacebook": "",
            "strTwitter": "",
            "strInstagram": "",
            "strDescriptionEN": "Henan Phoenix is a Chinese professional women's basketball club based in Henan, playing in the Women's Chinese Basketball Association (WCBA). Before 2014 it was known as Henan Elephants. The team is sometimes known by the name of its sponsor Yichuan Rural Commercial Bank (a bank based in Yichuan County, Henan).",
            "strDescriptionDE": null,
            "strDescriptionFR": null,
            "strDescriptionCN": null,
            "strDescriptionIT": null,
            "strDescriptionJP": null,
            "strDescriptionRU": null,
            "strDescriptionES": null,
            "strDescriptionPT": null,
            "strDescriptionSE": null,
            "strDescriptionNL": null,
            "strDescriptionHU": null,
            "strDescriptionNO": null,
            "strDescriptionIL": null,
            "strDescriptionPL": null,
            "strColour1": "",
            "strColour2": "",
            "strColour3": "",
            "strGender": "Male",
            "strCountry": "China",
            "strBadge": "https:\/\/r2.thesportsdb.com\/images\/media\/team\/badge\/8k9mmp1714043714.png",
            "strLogo": null,
            "strFanart1": null,
            "strFanart2": null,
            "strFanart3": null,
            "strFanart4": null,
            "strBanner": null,
            "strEquipment": null,
            "strYoutube": "",
            "strLocked": "unlocked"
        },
        {
            "idTeam": "144928",
            "idESPN": null,
            "idAPIfootball": "2569",
            "intLoved": null,
            "strTeam": "Inner Mongolia",
            "strTeamAlternate": "",
            "strTeamShort": null,
            "intFormedYear": "0",
            "strSport": "Basketball",
            "strLeague": "Chinese WCBA",
            "idLeague": "5131",
            "strLeague2": "",
            "idLeague2": null,
            "strLeague3": "",
            "idLeague3": null,
            "strLeague4": "",
            "idLeague4": null,
            "strLeague5": "",
            "idLeague5": null,
            "strLeague6": "",
            "idLeague6": null,
            "strLeague7": "",
            "idLeague7": null,
            "strDivision": null,
            "idVenue": null,
            "strStadium": "",
            "strKeywords": "",
            "strRSS": "",
            "strLocation": "",
            "intStadiumCapacity": "0",
            "strWebsite": "",
            "strFacebook": "",
            "strTwitter": "",
            "strInstagram": "",
            "strDescriptionEN": null,
            "strDescriptionDE": null,
            "strDescriptionFR": null,
            "strDescriptionCN": null,
            "strDescriptionIT": null,
            "strDescriptionJP": null,
            "strDescriptionRU": null,
            "strDescriptionES": null,
            "strDescriptionPT": null,
            "strDescriptionSE": null,
            "strDescriptionNL": null,
            "strDescriptionHU": null,
            "strDescriptionNO": null,
            "strDescriptionIL": null,
            "strDescriptionPL": null,
            "strColour1": null,
            "strColour2": null,
            "strColour3": null,
            "strGender": "Male",
            "strCountry": "Mongolia",
            "strBadge": "https:\/\/r2.thesportsdb.com\/images\/media\/team\/badge\/slba4j1704741319.png",
            "strLogo": null,
            "strFanart1": null,
            "strFanart2": null,
            "strFanart3": null,
            "strFanart4": null,
            "strBanner": null,
            "strEquipment": null,
            "strYoutube": "",
            "strLocked": "unlocked"
        },
        {
            "idTeam": "144594",
            "idESPN": null,
            "idAPIfootball": "2570",
            "intLoved": null,
            "strTeam": "Jiangsu Phoenix",
            "strTeamAlternate": "",
            "strTeamShort": null,
            "intFormedYear": "2002",
            "strSport": "Basketball",
            "strLeague": "Chinese WCBA",
            "idLeague": "5131",
            "strLeague2": "",
            "idLeague2": null,
            "strLeague3": "",
            "idLeague3": null,
            "strLeague4": "",
            "idLeague4": null,
            "strLeague5": "",
            "idLeague5": null,
            "strLeague6": "",
            "idLeague6": null,
            "strLeague7": "",
            "idLeague7": null,
            "strDivision": null,
            "idVenue": null,
            "strStadium": "Liyang Stadium",
            "strKeywords": "",
            "strRSS": "",
            "strLocation": "Liyang",
            "intStadiumCapacity": "4500",
            "strWebsite": "",
            "strFacebook": "",
            "strTwitter": "",
            "strInstagram": "",
            "strDescriptionEN": "Jiangsu Phoenix is a Chinese professional women's basketball club based in Jiangsu, playing in the Women's Chinese Basketball Association (WCBA).",
            "strDescriptionDE": null,
            "strDescriptionFR": null,
            "strDescriptionCN": null,
            "strDescriptionIT": null,
            "strDescriptionJP": null,
            "strDescriptionRU": null,
            "strDescriptionES": null,
            "strDescriptionPT": null,
            "strDescriptionSE": null,
            "strDescriptionNL": null,
            "strDescriptionHU": null,
            "strDescriptionNO": null,
            "strDescriptionIL": null,
            "strDescriptionPL": null,
            "strColour1": null,
            "strColour2": null,
            "strColour3": null,
            "strGender": "Female",
            "strCountry": "China",
            "strBadge": "https:\/\/r2.thesportsdb.com\/images\/media\/team\/badge\/mxzt0y1704744615.png",
            "strLogo": null,
            "strFanart1": null,
            "strFanart2": null,
            "strFanart3": null,
            "strFanart4": null,
            "strBanner": null,
            "strEquipment": null,
            "strYoutube": "",
            "strLocked": "unlocked"
        },
        {
            "idTeam": "144595",
            "idESPN": null,
            "idAPIfootball": "2580",
            "intLoved": null,
            "strTeam": "Liaoning Flying Eagles",
            "strTeamAlternate": "",
            "strTeamShort": null,
            "intFormedYear": "2002",
            "strSport": "Basketball",
            "strLeague": "Chinese WCBA",
            "idLeague": "5131",
            "strLeague2": "",
            "idLeague2": null,
            "strLeague3": "",
            "idLeague3": null,
            "strLeague4": "",
            "idLeague4": null,
            "strLeague5": "",
            "idLeague5": null,
            "strLeague6": "",
            "idLeague6": null,
            "strLeague7": "",
            "idLeague7": null,
            "strDivision": null,
            "idVenue": null,
            "strStadium": "Angang Stadium",
            "strKeywords": "",
            "strRSS": "",
            "strLocation": "Anshan",
            "intStadiumCapacity": "5000",
            "strWebsite": "",
            "strFacebook": "",
            "strTwitter": "",
            "strInstagram": "",
            "strDescriptionEN": "Liaoning Zhongda Aluminium Flying Eagles (simplified Chinese: 辽宁忠大铝业飞鹰; traditional Chinese: 遼寧忠大鋁業飛鷹; pinyin: liáo níng zhōng dà lǚ yè fēi yīng) is a Chinese professional women's basketball club in Liaoning, playing in the Women's Chinese Basketball Association (WCBA). Liaoning Zhongda Aluminum Co. has been the team's corporate sponsor since 2015.\r\n\r\nFrom 2005 to 2015, the team was known as Liaoning Hengye Golden Leopards and sponsored by Liaoning Hengye Group. Before 2005 it was known as Liaoning Big Dipper (辽宁北斗星女篮).",
            "strDescriptionDE": null,
            "strDescriptionFR": null,
            "strDescriptionCN": null,
            "strDescriptionIT": null,
            "strDescriptionJP": null,
            "strDescriptionRU": null,
            "strDescriptionES": null,
            "strDescriptionPT": null,
            "strDescriptionSE": null,
            "strDescriptionNL": null,
            "strDescriptionHU": null,
            "strDescriptionNO": null,
            "strDescriptionIL": null,
            "strDescriptionPL": null,
            "strColour1": null,
            "strColour2": null,
            "strColour3": null,
            "strGender": "Female",
            "strCountry": "China",
            "strBadge": "https:\/\/r2.thesportsdb.com\/images\/media\/team\/badge\/uof29m1638031928.png",
            "strLogo": null,
            "strFanart1": null,
            "strFanart2": null,
            "strFanart3": null,
            "strFanart4": null,
            "strBanner": null,
            "strEquipment": null,
            "strYoutube": "",
            "strLocked": "unlocked"
        },
        {
            "idTeam": "144596",
            "idESPN": null,
            "idAPIfootball": "2571",
            "intLoved": null,
            "strTeam": "Shaanxi Red Wolves",
            "strTeamAlternate": "",
            "strTeamShort": null,
            "intFormedYear": "2017",
            "strSport": "Basketball",
            "strLeague": "Chinese WCBA",
            "idLeague": "5131",
            "strLeague2": "",
            "idLeague2": null,
            "strLeague3": "",
            "idLeague3": null,
            "strLeague4": "",
            "idLeague4": null,
            "strLeague5": "",
            "idLeague5": null,
            "strLeague6": "",
            "idLeague6": null,
            "strLeague7": "",
            "idLeague7": null,
            "strDivision": null,
            "idVenue": null,
            "strStadium": "Weinan Sports Centre",
            "strKeywords": "",
            "strRSS": "",
            "strLocation": "Weinan",
            "intStadiumCapacity": "3500",
            "strWebsite": "",
            "strFacebook": "",
            "strTwitter": "",
            "strInstagram": "",
            "strDescriptionEN": "The Shaanxi Tianze Red Wolves are a Chinese professional women's basketball club based in Weinan, Shaanxi, playing in the Women's Chinese Basketball Association (WCBA). The team is owned by the Tianze Group.",
            "strDescriptionDE": null,
            "strDescriptionFR": null,
            "strDescriptionCN": null,
            "strDescriptionIT": null,
            "strDescriptionJP": null,
            "strDescriptionRU": null,
            "strDescriptionES": null,
            "strDescriptionPT": null,
            "strDescriptionSE": null,
            "strDescriptionNL": null,
            "strDescriptionHU": null,
            "strDescriptionNO": null,
            "strDescriptionIL": null,
            "strDescriptionPL": null,
            "strColour1": null,
            "strColour2": null,
            "strColour3": null,
            "strGender": "Female",
            "strCountry": "China",
            "strBadge": "https:\/\/r2.thesportsdb.com\/images\/media\/team\/badge\/20dk2f1638031932.png",
            "strLogo": null,
            "strFanart1": null,
            "strFanart2": null,
            "strFanart3": null,
            "strFanart4": null,
            "strBanner": null,
            "strEquipment": null,
            "strYoutube": "",
            "strLocked": "unlocked"
        },
        {
            "idTeam": "144929",
            "idESPN": null,
            "idAPIfootball": "2572",
            "intLoved": null,
            "strTeam": "Shandong Women",
            "strTeamAlternate": "",
            "strTeamShort": null,
            "intFormedYear": "0",
            "strSport": "Basketball",
            "strLeague": "Chinese WCBA",
            "idLeague": "5131",
            "strLeague2": "",
            "idLeague2": null,
            "strLeague3": "",
            "idLeague3": null,
            "strLeague4": "",
            "idLeague4": null,
            "strLeague5": "",
            "idLeague5": null,
            "strLeague6": "",
            "idLeague6": null,
            "strLeague7": "",
            "idLeague7": null,
            "strDivision": null,
            "idVenue": null,
            "strStadium": "",
            "strKeywords": "",
            "strRSS": "",
            "strLocation": "",
            "intStadiumCapacity": "0",
            "strWebsite": "",
            "strFacebook": "",
            "strTwitter": "",
            "strInstagram": "",
            "strDescriptionEN": null,
            "strDescriptionDE": null,
            "strDescriptionFR": null,
            "strDescriptionCN": null,
            "strDescriptionIT": null,
            "strDescriptionJP": null,
            "strDescriptionRU": null,
            "strDescriptionES": null,
            "strDescriptionPT": null,
            "strDescriptionSE": null,
            "strDescriptionNL": null,
            "strDescriptionHU": null,
            "strDescriptionNO": null,
            "strDescriptionIL": null,
            "strDescriptionPL": null,
            "strColour1": null,
            "strColour2": null,
            "strColour3": null,
            "strGender": "Male",
            "strCountry": "China",
            "strBadge": "https:\/\/r2.thesportsdb.com\/images\/media\/team\/badge\/uh4ega1642017569.png",
            "strLogo": null,
            "strFanart1": null,
            "strFanart2": null,
            "strFanart3": null,
            "strFanart4": null,
            "strBanner": null,
            "strEquipment": null,
            "strYoutube": "",
            "strLocked": "unlocked"
        },
        {
            "idTeam": "144597",
            "idESPN": null,
            "idAPIfootball": "2573",
            "intLoved": null,
            "strTeam": "Shanghai Swordfish",
            "strTeamAlternate": "",
            "strTeamShort": null,
            "intFormedYear": "2002",
            "strSport": "Basketball",
            "strLeague": "Chinese WCBA",
            "idLeague": "5131",
            "strLeague2": "",
            "idLeague2": null,
            "strLeague3": "",
            "idLeague3": null,
            "strLeague4": "",
            "idLeague4": null,
            "strLeague5": "",
            "idLeague5": null,
            "strLeague6": "",
            "idLeague6": null,
            "strLeague7": "",
            "idLeague7": null,
            "strDivision": null,
            "idVenue": null,
            "strStadium": "Baoshan Sports Centre \/ Baosteel Sports Centre",
            "strKeywords": "",
            "strRSS": "",
            "strLocation": "Shanghai",
            "intStadiumCapacity": "0",
            "strWebsite": "",
            "strFacebook": "",
            "strTwitter": "",
            "strInstagram": "",
            "strDescriptionEN": "Shanghai Baoshan Dahua Swordfish is a Chinese professional women's basketball club based in Shanghai, playing in the Women's Chinese Basketball Association (WCBA). It is co-owned by Baoshan District government, Shanghai Sports Institute, and Dahua Group. Before 2014 it was known as Shanghai Octopus, affiliated with the Shanghai Media Group. Between 2007 and 2008 it was sponsored by the Xiyang Group.",
            "strDescriptionDE": null,
            "strDescriptionFR": null,
            "strDescriptionCN": null,
            "strDescriptionIT": null,
            "strDescriptionJP": null,
            "strDescriptionRU": null,
            "strDescriptionES": null,
            "strDescriptionPT": null,
            "strDescriptionSE": null,
            "strDescriptionNL": null,
            "strDescriptionHU": null,
            "strDescriptionNO": null,
            "strDescriptionIL": null,
            "strDescriptionPL": null,
            "strColour1": null,
            "strColour2": null,
            "strColour3": null,
            "strGender": "Female",
            "strCountry": "China",
            "strBadge": "https:\/\/r2.thesportsdb.com\/images\/media\/team\/badge\/l4bio41638031937.png",
            "strLogo": null,
            "strFanart1": null,
            "strFanart2": null,
            "strFanart3": null,
            "strFanart4": null,
            "strBanner": null,
            "strEquipment": null,
            "strYoutube": "",
            "strLocked": "unlocked"
        },
        {
            "idTeam": "144598",
            "idESPN": null,
            "idAPIfootball": "2574",
            "intLoved": null,
            "strTeam": "Shanxi Flame",
            "strTeamAlternate": "",
            "strTeamShort": null,
            "intFormedYear": "2011",
            "strSport": "Basketball",
            "strLeague": "Chinese WCBA",
            "idLeague": "5131",
            "strLeague2": "",
            "idLeague2": null,
            "strLeague3": "",
            "idLeague3": null,
            "strLeague4": "",
            "idLeague4": null,
            "strLeague5": "",
            "idLeague5": null,
            "strLeague6": "",
            "idLeague6": null,
            "strLeague7": "",
            "idLeague7": null,
            "strDivision": null,
            "idVenue": null,
            "strStadium": "Shanxi Sports Centre Stadium",
            "strKeywords": "",
            "strRSS": "",
            "strLocation": "Taiyuan",
            "intStadiumCapacity": "8000",
            "strWebsite": "",
            "strFacebook": "",
            "strTwitter": "",
            "strInstagram": "",
            "strDescriptionEN": "Shanxi Xing Rui Flame is a professional women's basketball club located in Taiyuan, Shanxi, China, playing in the Women's Chinese Basketball Association (WCBA). It is also known by its sponsor's name Zhuyeqing. Led by WNBA star Maya Moore, the club won 3 consecutive WCBA championships from 2013 to 2015.",
            "strDescriptionDE": null,
            "strDescriptionFR": null,
            "strDescriptionCN": null,
            "strDescriptionIT": null,
            "strDescriptionJP": null,
            "strDescriptionRU": null,
            "strDescriptionES": null,
            "strDescriptionPT": null,
            "strDescriptionSE": null,
            "strDescriptionNL": null,
            "strDescriptionHU": null,
            "strDescriptionNO": null,
            "strDescriptionIL": null,
            "strDescriptionPL": null,
            "strColour1": null,
            "strColour2": null,
            "strColour3": null,
            "strGender": "Female",
            "strCountry": "China",
            "strBadge": "https:\/\/r2.thesportsdb.com\/images\/media\/team\/badge\/ha65sf1638031942.png",
            "strLogo": null,
            "strFanart1": null,
            "strFanart2": null,
            "strFanart3": null,
            "strFanart4": null,
            "strBanner": null,
            "strEquipment": null,
            "strYoutube": "",
            "strLocked": "unlocked"
        },
        {
            "idTeam": "144930",
            "idESPN": null,
            "idAPIfootball": "2575",
            "intLoved": null,
            "strTeam": "Sichuan Blue Whales Women",
            "strTeamAlternate": "",
            "strTeamShort": null,
            "intFormedYear": "0",
            "strSport": "Basketball",
            "strLeague": "Chinese WCBA",
            "idLeague": "5131",
            "strLeague2": "",
            "idLeague2": null,
            "strLeague3": "",
            "idLeague3": null,
            "strLeague4": "",
            "idLeague4": null,
            "strLeague5": "",
            "idLeague5": null,
            "strLeague6": "",
            "idLeague6": null,
            "strLeague7": "",
            "idLeague7": null,
            "strDivision": null,
            "idVenue": null,
            "strStadium": "",
            "strKeywords": "",
            "strRSS": "",
            "strLocation": "",
            "intStadiumCapacity": "0",
            "strWebsite": "",
            "strFacebook": "",
            "strTwitter": "",
            "strInstagram": "",
            "strDescriptionEN": null,
            "strDescriptionDE": null,
            "strDescriptionFR": null,
            "strDescriptionCN": null,
            "strDescriptionIT": null,
            "strDescriptionJP": null,
            "strDescriptionRU": null,
            "strDescriptionES": null,
            "strDescriptionPT": null,
            "strDescriptionSE": null,
            "strDescriptionNL": null,
            "strDescriptionHU": null,
            "strDescriptionNO": null,
            "strDescriptionIL": null,
            "strDescriptionPL": null,
            "strColour1": null,
            "strColour2": null,
            "strColour3": null,
            "strGender": "Male",
            "strCountry": "China",
            "strBadge": "https:\/\/r2.thesportsdb.com\/images\/media\/team\/badge\/6xa3uo1642017574.png",
            "strLogo": null,
            "strFanart1": null,
            "strFanart2": null,
            "strFanart3": null,
            "strFanart4": null,
            "strBanner": null,
            "strEquipment": null,
            "strYoutube": "",
            "strLocked": "unlocked"
        },
        {
            "idTeam": "144931",
            "idESPN": null,
            "idAPIfootball": "2576",
            "intLoved": null,
            "strTeam": "Tianjin Ronggang Women",
            "strTeamAlternate": "",
            "strTeamShort": null,
            "intFormedYear": "0",
            "strSport": "Basketball",
            "strLeague": "Chinese WCBA",
            "idLeague": "5131",
            "strLeague2": "",
            "idLeague2": null,
            "strLeague3": "",
            "idLeague3": null,
            "strLeague4": "",
            "idLeague4": null,
            "strLeague5": "",
            "idLeague5": null,
            "strLeague6": "",
            "idLeague6": null,
            "strLeague7": "",
            "idLeague7": null,
            "strDivision": null,
            "idVenue": null,
            "strStadium": "",
            "strKeywords": "",
            "strRSS": "",
            "strLocation": "",
            "intStadiumCapacity": "0",
            "strWebsite": "",
            "strFacebook": "",
            "strTwitter": "",
            "strInstagram": "",
            "strDescriptionEN": null,
            "strDescriptionDE": null,
            "strDescriptionFR": null,
            "strDescriptionCN": null,
            "strDescriptionIT": null,
            "strDescriptionJP": null,
            "strDescriptionRU": null,
            "strDescriptionES": null,
            "strDescriptionPT": null,
            "strDescriptionSE": null,
            "strDescriptionNL": null,
            "strDescriptionHU": null,
            "strDescriptionNO": null,
            "strDescriptionIL": null,
            "strDescriptionPL": null,
            "strColour1": null,
            "strColour2": null,
            "strColour3": null,
            "strGender": "Male",
            "strCountry": "China",
            "strBadge": "https:\/\/r2.thesportsdb.com\/images\/media\/team\/badge\/ep2bxv1704744685.png",
            "strLogo": null,
            "strFanart1": null,
            "strFanart2": null,
            "strFanart3": null,
            "strFanart4": null,
            "strBanner": null,
            "strEquipment": null,
            "strYoutube": "",
            "strLocked": "unlocked"
        },
        {
            "idTeam": "144932",
            "idESPN": null,
            "idAPIfootball": "2577",
            "intLoved": null,
            "strTeam": "Wuhan Shengfan",
            "strTeamAlternate": "",
            "strTeamShort": null,
            "intFormedYear": "0",
            "strSport": "Basketball",
            "strLeague": "Chinese WCBA",
            "idLeague": "5131",
            "strLeague2": "",
            "idLeague2": null,
            "strLeague3": "",
            "idLeague3": null,
            "strLeague4": "",
            "idLeague4": null,
            "strLeague5": "",
            "idLeague5": null,
            "strLeague6": "",
            "idLeague6": null,
            "strLeague7": "",
            "idLeague7": null,
            "strDivision": null,
            "idVenue": null,
            "strStadium": "",
            "strKeywords": "",
            "strRSS": "",
            "strLocation": "",
            "intStadiumCapacity": "0",
            "strWebsite": "",
            "strFacebook": "",
            "strTwitter": "",
            "strInstagram": "",
            "strDescriptionEN": null,
            "strDescriptionDE": null,
            "strDescriptionFR": null,
            "strDescriptionCN": null,
            "strDescriptionIT": null,
            "strDescriptionJP": null,
            "strDescriptionRU": null,
            "strDescriptionES": null,
            "strDescriptionPT": null,
            "strDescriptionSE": null,
            "strDescriptionNL": null,
            "strDescriptionHU": null,
            "strDescriptionNO": null,
            "strDescriptionIL": null,
            "strDescriptionPL": null,
            "strColour1": null,
            "strColour2": null,
            "strColour3": null,
            "strGender": "Male",
            "strCountry": "China",
            "strBadge": "https:\/\/r2.thesportsdb.com\/images\/media\/team\/badge\/nohkn01704741157.png",
            "strLogo": null,
            "strFanart1": null,
            "strFanart2": null,
            "strFanart3": null,
            "strFanart4": null,
            "strBanner": null,
            "strEquipment": null,
            "strYoutube": "",
            "strLocked": "unlocked"
        },
        {
            "idTeam": "148320",
            "idESPN": null,
            "idAPIfootball": "6269",
            "intLoved": null,
            "strTeam": "Xiamen Women",
            "strTeamAlternate": "",
            "strTeamShort": "",
            "intFormedYear": "0",
            "strSport": "Basketball",
            "strLeague": "Chinese WCBA",
            "idLeague": "5131",
            "strLeague2": "",
            "idLeague2": null,
            "strLeague3": "",
            "idLeague3": null,
            "strLeague4": "",
            "idLeague4": null,
            "strLeague5": "",
            "idLeague5": null,
            "strLeague6": "",
            "idLeague6": null,
            "strLeague7": "",
            "idLeague7": null,
            "strDivision": null,
            "idVenue": null,
            "strStadium": "",
            "strKeywords": "",
            "strRSS": "",
            "strLocation": "",
            "intStadiumCapacity": "0",
            "strWebsite": "",
            "strFacebook": "",
            "strTwitter": "",
            "strInstagram": "",
            "strDescriptionEN": "The Xiamen Women's basketball team is a highly skilled and competitive team based in Xiamen, China. Comprised of talented and dedicated female athletes, this team has established itself as a force to be reckoned with in the world of basketball.\r\n\r\nKnown for their exceptional teamwork and strategic play, the Xiamen Women's team consistently displays a high level of skill and determination on the court. Their players possess a strong basketball IQ and are adept at executing both offensive and defensive plays.\r\n\r\nThe team's roster is filled with versatile and dynamic players who excel in various positions. From agile guards who can drive to the basket and shoot from long range, to powerful forwards who dominate the paint and grab rebounds, the Xiamen Women's team boasts a well-rounded lineup.\r\n\r\nCoached by experienced and knowledgeable mentors, the team is constantly refining their skills and tactics to stay ahead of the competition. Their commitment to continuous improvement is evident in their disciplined training sessions and meticulous game preparation.\r\n\r\nOff the court, the Xiamen Women's team is known for their sportsmanship and dedication to their community. They actively engage in charitable initiatives and youth development programs, inspiring the next generation of basketball players.\r\n\r\nWith a strong fan base and a reputation for excellence, the Xiamen Women's basketball team is a source of pride for the city of Xiamen. Their electrifying performances and unwavering determination make them a formidable opponent in any competition they participate in.",
            "strDescriptionDE": null,
            "strDescriptionFR": null,
            "strDescriptionCN": null,
            "strDescriptionIT": null,
            "strDescriptionJP": null,
            "strDescriptionRU": null,
            "strDescriptionES": null,
            "strDescriptionPT": null,
            "strDescriptionSE": null,
            "strDescriptionNL": null,
            "strDescriptionHU": null,
            "strDescriptionNO": null,
            "strDescriptionIL": null,
            "strDescriptionPL": null,
            "strColour1": "",
            "strColour2": "",
            "strColour3": "",
            "strGender": "Male",
            "strCountry": "China",
            "strBadge": "https:\/\/r2.thesportsdb.com\/images\/media\/team\/badge\/a70ufm1714044060.png",
            "strLogo": null,
            "strFanart1": null,
            "strFanart2": null,
            "strFanart3": null,
            "strFanart4": null,
            "strBanner": null,
            "strEquipment": null,
            "strYoutube": "",
            "strLocked": "unlocked"
        },
        {
            "idTeam": "144599",
            "idESPN": null,
            "idAPIfootball": "2578",
            "intLoved": null,
            "strTeam": "Xinjiang Magic Deer",
            "strTeamAlternate": "",
            "strTeamShort": null,
            "intFormedYear": "2015",
            "strSport": "Basketball",
            "strLeague": "Chinese WCBA",
            "idLeague": "5131",
            "strLeague2": "",
            "idLeague2": null,
            "strLeague3": "",
            "idLeague3": null,
            "strLeague4": "",
            "idLeague4": null,
            "strLeague5": "",
            "idLeague5": null,
            "strLeague6": "",
            "idLeague6": null,
            "strLeague7": "",
            "idLeague7": null,
            "strDivision": null,
            "idVenue": null,
            "strStadium": "Changji Stadium",
            "strKeywords": "",
            "strRSS": "",
            "strLocation": "Changji",
            "intStadiumCapacity": "0",
            "strWebsite": "",
            "strFacebook": "",
            "strTwitter": "",
            "strInstagram": "",
            "strDescriptionEN": "Xinjiang Tian Shan Magic Deer is a Chinese professional women's basketball club based in Ürümqi, Xinjiang, playing in the Women's Chinese Basketball Association (WCBA). The team also plays some home games in Changji.\r\n\r\nThe nickname Tian Shan magic deer is derived from Tian Shan wapiti, an elk subspecies native to Tian Shan in Xinjiang.",
            "strDescriptionDE": null,
            "strDescriptionFR": null,
            "strDescriptionCN": null,
            "strDescriptionIT": null,
            "strDescriptionJP": null,
            "strDescriptionRU": null,
            "strDescriptionES": null,
            "strDescriptionPT": null,
            "strDescriptionSE": null,
            "strDescriptionNL": null,
            "strDescriptionHU": null,
            "strDescriptionNO": null,
            "strDescriptionIL": null,
            "strDescriptionPL": null,
            "strColour1": null,
            "strColour2": null,
            "strColour3": null,
            "strGender": "Female",
            "strCountry": "China",
            "strBadge": "https:\/\/r2.thesportsdb.com\/images\/media\/team\/badge\/oiadnj1638031946.png",
            "strLogo": null,
            "strFanart1": null,
            "strFanart2": null,
            "strFanart3": null,
            "strFanart4": null,
            "strBanner": null,
            "strEquipment": null,
            "strYoutube": "",
            "strLocked": "unlocked"
        },
        {
            "idTeam": "144933",
            "idESPN": null,
            "idAPIfootball": "2579",
            "intLoved": null,
            "strTeam": "Zhejiang Golden Bulls",
            "strTeamAlternate": "",
            "strTeamShort": null,
            "intFormedYear": "0",
            "strSport": "Basketball",
            "strLeague": "Chinese WCBA",
            "idLeague": "5131",
            "strLeague2": "",
            "idLeague2": null,
            "strLeague3": "",
            "idLeague3": null,
            "strLeague4": "",
            "idLeague4": null,
            "strLeague5": "",
            "idLeague5": null,
            "strLeague6": "",
            "idLeague6": null,
            "strLeague7": "",
            "idLeague7": null,
            "strDivision": null,
            "idVenue": null,
            "strStadium": "",
            "strKeywords": "",
            "strRSS": "",
            "strLocation": "",
            "intStadiumCapacity": "0",
            "strWebsite": "",
            "strFacebook": "",
            "strTwitter": "",
            "strInstagram": "",
            "strDescriptionEN": null,
            "strDescriptionDE": null,
            "strDescriptionFR": null,
            "strDescriptionCN": null,
            "strDescriptionIT": null,
            "strDescriptionJP": null,
            "strDescriptionRU": null,
            "strDescriptionES": null,
            "strDescriptionPT": null,
            "strDescriptionSE": null,
            "strDescriptionNL": null,
            "strDescriptionHU": null,
            "strDescriptionNO": null,
            "strDescriptionIL": null,
            "strDescriptionPL": null,
            "strColour1": null,
            "strColour2": null,
            "strColour3": null,
            "strGender": "Male",
            "strCountry": "China",
            "strBadge": "https:\/\/r2.thesportsdb.com\/images\/media\/team\/badge\/bcleqy1642017588.png",
            "strLogo": null,
            "strFanart1": null,
            "strFanart2": null,
            "strFanart3": null,
            "strFanart4": null,
            "strBanner": null,
            "strEquipment": null,
            "strYoutube": "",
            "strLocked": "unlocked"
        }
    ]
}