{
    "teams": [
        {
            "idTeam": "144249",
            "idESPN": null,
            "idAPIfootball": "9823",
            "intLoved": null,
            "strTeam": "Águilas",
            "strTeamAlternate": "",
            "strTeamShort": "",
            "intFormedYear": "2010",
            "strSport": "Soccer",
            "strLeague": "Spanish Segunda RFEF Group 4",
            "idLeague": "5091",
            "strLeague2": "Copa del Rey",
            "idLeague2": "4483",
            "strLeague3": "",
            "idLeague3": null,
            "strLeague4": "",
            "idLeague4": null,
            "strLeague5": "",
            "idLeague5": null,
            "strLeague6": "",
            "idLeague6": null,
            "strLeague7": "",
            "idLeague7": null,
            "strDivision": null,
            "idVenue": null,
            "strStadium": "El Rubial",
            "strKeywords": "",
            "strRSS": "",
            "strLocation": "Águilas",
            "intStadiumCapacity": "4000",
            "strWebsite": "",
            "strFacebook": "",
            "strTwitter": "",
            "strInstagram": "",
            "strDescriptionEN": "Águilas Fútbol Club is a Spanish football club based in Águilas, in the autonomous community of Murcia. Founded in 2010, the club plays in Segunda División RFEF – Group 5, holding home games at Estadio El Rubial, with a 4,000 seat capacity.",
            "strDescriptionDE": null,
            "strDescriptionFR": null,
            "strDescriptionCN": null,
            "strDescriptionIT": null,
            "strDescriptionJP": null,
            "strDescriptionRU": null,
            "strDescriptionES": null,
            "strDescriptionPT": null,
            "strDescriptionSE": null,
            "strDescriptionNL": null,
            "strDescriptionHU": null,
            "strDescriptionNO": null,
            "strDescriptionIL": null,
            "strDescriptionPL": null,
            "strColour1": "",
            "strColour2": "",
            "strColour3": "",
            "strGender": "Male",
            "strCountry": "Spain",
            "strBadge": "https:\/\/r2.thesportsdb.com\/images\/media\/team\/badge\/h70lhf1677639069.png",
            "strLogo": null,
            "strFanart1": null,
            "strFanart2": null,
            "strFanart3": null,
            "strFanart4": null,
            "strBanner": null,
            "strEquipment": null,
            "strYoutube": "",
            "strLocked": "unlocked"
        },
        {
            "idTeam": "144940",
            "idESPN": null,
            "idAPIfootball": "9741",
            "intLoved": null,
            "strTeam": "Almeria B",
            "strTeamAlternate": "UD Almería B, Unión Deportiva Almería B",
            "strTeamShort": "",
            "intFormedYear": "2001",
            "strSport": "Soccer",
            "strLeague": "Spanish Segunda RFEF Group 4",
            "idLeague": "5091",
            "strLeague2": "",
            "idLeague2": null,
            "strLeague3": "",
            "idLeague3": null,
            "strLeague4": "",
            "idLeague4": null,
            "strLeague5": "",
            "idLeague5": null,
            "strLeague6": "",
            "idLeague6": null,
            "strLeague7": "",
            "idLeague7": null,
            "strDivision": null,
            "idVenue": "0",
            "strStadium": "Anexo al Estadio de los Juegos Mediterráneos",
            "strKeywords": "",
            "strRSS": "",
            "strLocation": "Almería, Spain",
            "intStadiumCapacity": "350",
            "strWebsite": "www.udalmeriasad.com",
            "strFacebook": "",
            "strTwitter": "",
            "strInstagram": "",
            "strDescriptionEN": "Unión Deportiva Almería \"B\" is a Spanish football team based in Almería, in the autonomous community of Andalusia. Founded in 2001, it is the reserve team of UD Almería and currently plays in Tercera División RFEF – Group 9, holding home games at Anexo al Estadio de los Juegos Mediterráneos, with a 350 seat capacity.",
            "strDescriptionDE": null,
            "strDescriptionFR": null,
            "strDescriptionCN": null,
            "strDescriptionIT": null,
            "strDescriptionJP": null,
            "strDescriptionRU": null,
            "strDescriptionES": null,
            "strDescriptionPT": null,
            "strDescriptionSE": null,
            "strDescriptionNL": null,
            "strDescriptionHU": null,
            "strDescriptionNO": null,
            "strDescriptionIL": null,
            "strDescriptionPL": null,
            "strColour1": "",
            "strColour2": "",
            "strColour3": "",
            "strGender": "Male",
            "strCountry": "Spain",
            "strBadge": "https:\/\/r2.thesportsdb.com\/images\/media\/team\/badge\/xm7v0l1642339270.png",
            "strLogo": null,
            "strFanart1": null,
            "strFanart2": null,
            "strFanart3": null,
            "strFanart4": null,
            "strBanner": null,
            "strEquipment": null,
            "strYoutube": "",
            "strLocked": "unlocked"
        },
        {
            "idTeam": "147603",
            "idESPN": null,
            "idAPIfootball": "7522",
            "intLoved": null,
            "strTeam": "Atlético Antoniano",
            "strTeamAlternate": "",
            "strTeamShort": "",
            "intFormedYear": "1964",
            "strSport": "Soccer",
            "strLeague": "Spanish Segunda RFEF Group 4",
            "idLeague": "5091",
            "strLeague2": "",
            "idLeague2": null,
            "strLeague3": "",
            "idLeague3": null,
            "strLeague4": "",
            "idLeague4": null,
            "strLeague5": "",
            "idLeague5": null,
            "strLeague6": "",
            "idLeague6": null,
            "strLeague7": "",
            "idLeague7": null,
            "strDivision": null,
            "idVenue": "0",
            "strStadium": "Municipal de Lebrija",
            "strKeywords": "",
            "strRSS": "",
            "strLocation": "Lebrija, Spain",
            "intStadiumCapacity": "0",
            "strWebsite": "",
            "strFacebook": "www.facebook.com\/CAAntoniano\/",
            "strTwitter": "",
            "strInstagram": "www.instagram.com\/caantoniano",
            "strDescriptionEN": "Club Atlético Antoniano is a Spanish football team based in Lebrija, Province of Seville, in the autonomous community of Andalusia. Founded in 1964, it plays in Tercera División – Group 10, holding home games at Estadio Municipal de Lebrija, with a capacity of 3,500 seats.",
            "strDescriptionDE": null,
            "strDescriptionFR": null,
            "strDescriptionCN": null,
            "strDescriptionIT": null,
            "strDescriptionJP": null,
            "strDescriptionRU": null,
            "strDescriptionES": null,
            "strDescriptionPT": null,
            "strDescriptionSE": null,
            "strDescriptionNL": null,
            "strDescriptionHU": null,
            "strDescriptionNO": null,
            "strDescriptionIL": null,
            "strDescriptionPL": null,
            "strColour1": "",
            "strColour2": "",
            "strColour3": "",
            "strGender": "Male",
            "strCountry": "Spain",
            "strBadge": "https:\/\/r2.thesportsdb.com\/images\/media\/team\/badge\/88mn8s1711252710.png",
            "strLogo": null,
            "strFanart1": null,
            "strFanart2": null,
            "strFanart3": null,
            "strFanart4": null,
            "strBanner": null,
            "strEquipment": null,
            "strYoutube": "",
            "strLocked": "unlocked"
        },
        {
            "idTeam": "138302",
            "idESPN": null,
            "idAPIfootball": "9598",
            "intLoved": null,
            "strTeam": "Cadiz Mirandilla",
            "strTeamAlternate": "Cádiz Club de Fútbol B, Cadiz II, Cadiz B,",
            "strTeamShort": null,
            "intFormedYear": "1974",
            "strSport": "Soccer",
            "strLeague": "Spanish Segunda RFEF Group 4",
            "idLeague": "5091",
            "strLeague2": "",
            "idLeague2": null,
            "strLeague3": "",
            "idLeague3": null,
            "strLeague4": "",
            "idLeague4": null,
            "strLeague5": "",
            "idLeague5": null,
            "strLeague6": "",
            "idLeague6": null,
            "strLeague7": "",
            "idLeague7": null,
            "strDivision": null,
            "idVenue": null,
            "strStadium": "Ramón Blanco",
            "strKeywords": "",
            "strRSS": "",
            "strLocation": "Cádiz, Spain",
            "intStadiumCapacity": "1700",
            "strWebsite": "www.cadizcf.com",
            "strFacebook": "",
            "strTwitter": "",
            "strInstagram": "",
            "strDescriptionEN": "Cádiz Club de Fútbol Mirandilla is a Spanish football team based in Cádiz, in the autonomous community of Andalusia. It's the reserve team of Cádiz CF. Founded in 1973, it currently plays in Segunda Federación – Group 4, holding home games at Estadio Ramón Blanco, with a 1,700-seat capacity.\r\n\r\nOn 16 June 2022, Cádiz B was renamed to Cádiz CF Mirandilla, as an honour to Mirandilla FC, the name of the first team between 1924 and 1936.",
            "strDescriptionDE": null,
            "strDescriptionFR": null,
            "strDescriptionCN": null,
            "strDescriptionIT": null,
            "strDescriptionJP": null,
            "strDescriptionRU": null,
            "strDescriptionES": null,
            "strDescriptionPT": null,
            "strDescriptionSE": null,
            "strDescriptionNL": null,
            "strDescriptionHU": null,
            "strDescriptionNO": null,
            "strDescriptionIL": null,
            "strDescriptionPL": null,
            "strColour1": "",
            "strColour2": "",
            "strColour3": "",
            "strGender": "Male",
            "strCountry": "Spain",
            "strBadge": "https:\/\/r2.thesportsdb.com\/images\/media\/team\/badge\/hpzb451688147689.png",
            "strLogo": null,
            "strFanart1": null,
            "strFanart2": null,
            "strFanart3": null,
            "strFanart4": null,
            "strBanner": null,
            "strEquipment": null,
            "strYoutube": "",
            "strLocked": "unlocked"
        },
        {
            "idTeam": "149458",
            "idESPN": null,
            "idAPIfootball": "9811",
            "intLoved": null,
            "strTeam": "Deportiva Minera",
            "strTeamAlternate": "CD Minera",
            "strTeamShort": "",
            "intFormedYear": "1927",
            "strSport": "Soccer",
            "strLeague": "Spanish Segunda RFEF Group 4",
            "idLeague": "5091",
            "strLeague2": "Copa del Rey",
            "idLeague2": "4483",
            "strLeague3": "",
            "idLeague3": null,
            "strLeague4": "",
            "idLeague4": null,
            "strLeague5": "",
            "idLeague5": null,
            "strLeague6": "",
            "idLeague6": null,
            "strLeague7": "",
            "idLeague7": null,
            "strDivision": null,
            "idVenue": "0",
            "strStadium": null,
            "strKeywords": "Águilas Rojas",
            "strRSS": "",
            "strLocation": "Llano del Beal, Cartagena, Spain",
            "intStadiumCapacity": null,
            "strWebsite": "",
            "strFacebook": "",
            "strTwitter": "",
            "strInstagram": "",
            "strDescriptionEN": "Club Deportiva Minera is a Spanish football team based in Llano del Beal, Cartagena, in the Region of Murcia. Founded in 1927 it plays in Segunda Federación – Group 4, holding home games at Estadio Municipal Ángel Celdrán, with a capacity of 2,000 seats.",
            "strDescriptionDE": null,
            "strDescriptionFR": null,
            "strDescriptionCN": null,
            "strDescriptionIT": null,
            "strDescriptionJP": null,
            "strDescriptionRU": null,
            "strDescriptionES": null,
            "strDescriptionPT": null,
            "strDescriptionSE": null,
            "strDescriptionNL": null,
            "strDescriptionHU": null,
            "strDescriptionNO": null,
            "strDescriptionIL": null,
            "strDescriptionPL": null,
            "strColour1": "",
            "strColour2": "",
            "strColour3": "",
            "strGender": "Male",
            "strCountry": "Spain",
            "strBadge": "https:\/\/r2.thesportsdb.com\/images\/media\/team\/badge\/8f49fi1730649884.png",
            "strLogo": null,
            "strFanart1": null,
            "strFanart2": null,
            "strFanart3": null,
            "strFanart4": null,
            "strBanner": null,
            "strEquipment": null,
            "strYoutube": "",
            "strLocked": "unlocked"
        },
        {
            "idTeam": "138304",
            "idESPN": null,
            "idAPIfootball": "5259",
            "intLoved": null,
            "strTeam": "Don Benito",
            "strTeamAlternate": "CD Don Benito, Club Deportivo Don Benito",
            "strTeamShort": "",
            "intFormedYear": "1928",
            "strSport": "Soccer",
            "strLeague": "Spanish Segunda RFEF Group 4",
            "idLeague": "5091",
            "strLeague2": "Copa del Rey",
            "idLeague2": "4483",
            "strLeague3": "",
            "idLeague3": null,
            "strLeague4": "",
            "idLeague4": null,
            "strLeague5": "",
            "idLeague5": null,
            "strLeague6": "",
            "idLeague6": null,
            "strLeague7": "",
            "idLeague7": null,
            "strDivision": null,
            "idVenue": "0",
            "strStadium": "Vicente Sanz",
            "strKeywords": "",
            "strRSS": "",
            "strLocation": "Don Benito, Spain",
            "intStadiumCapacity": "5000",
            "strWebsite": "cddonbenito.com",
            "strFacebook": "facebook.com\/clubdeportivodonbenito",
            "strTwitter": "twitter.com\/Cddonbenito1928",
            "strInstagram": "www.instagram.com\/cddonbenito",
            "strDescriptionEN": "Club Deportivo Don Benito is a Spanish football team based in Don Benito, in the autonomous community of Extremadura. Founded in 1928 it plays in Segunda División B, holding home matches at Estadio Vicente Sanz, with a capacity of 5,000 seats.",
            "strDescriptionDE": null,
            "strDescriptionFR": null,
            "strDescriptionCN": null,
            "strDescriptionIT": null,
            "strDescriptionJP": null,
            "strDescriptionRU": null,
            "strDescriptionES": null,
            "strDescriptionPT": null,
            "strDescriptionSE": null,
            "strDescriptionNL": null,
            "strDescriptionHU": null,
            "strDescriptionNO": null,
            "strDescriptionIL": null,
            "strDescriptionPL": null,
            "strColour1": "",
            "strColour2": "",
            "strColour3": "",
            "strGender": "Male",
            "strCountry": "Spain",
            "strBadge": "https:\/\/r2.thesportsdb.com\/images\/media\/team\/badge\/zs6ils1579988738.png",
            "strLogo": null,
            "strFanart1": null,
            "strFanart2": null,
            "strFanart3": null,
            "strFanart4": null,
            "strBanner": null,
            "strEquipment": null,
            "strYoutube": "www.youtube.com\/channel\/UCfm9INw5u1TTVPZNFKs6Gdw",
            "strLocked": "unlocked"
        },
        {
            "idTeam": "147605",
            "idESPN": null,
            "idAPIfootball": "15358",
            "intLoved": null,
            "strTeam": "Estepona",
            "strTeamAlternate": "",
            "strTeamShort": "",
            "intFormedYear": "2014",
            "strSport": "Soccer",
            "strLeague": "Spanish Segunda RFEF Group 4",
            "idLeague": "5091",
            "strLeague2": "Copa del Rey",
            "idLeague2": "4483",
            "strLeague3": "",
            "idLeague3": null,
            "strLeague4": "",
            "idLeague4": null,
            "strLeague5": "",
            "idLeague5": null,
            "strLeague6": "",
            "idLeague6": null,
            "strLeague7": "",
            "idLeague7": null,
            "strDivision": null,
            "idVenue": "0",
            "strStadium": "Francisco Muñoz Pérez",
            "strKeywords": "",
            "strRSS": "",
            "strLocation": "Estepona, Spain",
            "intStadiumCapacity": "3800",
            "strWebsite": "www.clubdeportivoestepona.com",
            "strFacebook": "www.facebook.com\/ClubDeportivoEstepona\/",
            "strTwitter": "twitter.com\/CDEstepona",
            "strInstagram": "www.instagram.com\/cdestepona",
            "strDescriptionEN": "Club Deportivo Estepona Fútbol Senior is a Spanish football team based in Estepona, Málaga, in the autonomous community of Andalucia. Founded in 2014, it plays in Segunda Federación – Group 5, holding home games at Estadio Municipal Francisco Muñoz Pérez, with a capacity of 3,800 people.",
            "strDescriptionDE": null,
            "strDescriptionFR": null,
            "strDescriptionCN": null,
            "strDescriptionIT": null,
            "strDescriptionJP": null,
            "strDescriptionRU": null,
            "strDescriptionES": null,
            "strDescriptionPT": null,
            "strDescriptionSE": null,
            "strDescriptionNL": null,
            "strDescriptionHU": null,
            "strDescriptionNO": null,
            "strDescriptionIL": null,
            "strDescriptionPL": null,
            "strColour1": "",
            "strColour2": "",
            "strColour3": "",
            "strGender": "Male",
            "strCountry": "Spain",
            "strBadge": "https:\/\/r2.thesportsdb.com\/images\/media\/team\/badge\/o4xaxy1711252447.png",
            "strLogo": null,
            "strFanart1": null,
            "strFanart2": null,
            "strFanart3": null,
            "strFanart4": null,
            "strBanner": null,
            "strEquipment": null,
            "strYoutube": "www.youtube.com\/channel\/UC31UWae0oVab9KAjFMJ1rxQ",
            "strLocked": "unlocked"
        },
        {
            "idTeam": "146798",
            "idESPN": null,
            "idAPIfootball": "15359",
            "intLoved": null,
            "strTeam": "Juventud Torremolinos",
            "strTeamAlternate": "Juventud de Torremolinos Club de Fútbol, Juventud de Torremolinos CF",
            "strTeamShort": "",
            "intFormedYear": "1958",
            "strSport": "Soccer",
            "strLeague": "Spanish Segunda RFEF Group 4",
            "idLeague": "5091",
            "strLeague2": "Copa del Rey",
            "idLeague2": "4483",
            "strLeague3": "",
            "idLeague3": null,
            "strLeague4": "",
            "idLeague4": null,
            "strLeague5": "",
            "idLeague5": null,
            "strLeague6": "",
            "idLeague6": null,
            "strLeague7": "",
            "idLeague7": null,
            "strDivision": null,
            "idVenue": "0",
            "strStadium": "El Pozuelo",
            "strKeywords": "",
            "strRSS": "",
            "strLocation": "Torremolinos, Spain",
            "intStadiumCapacity": "3000",
            "strWebsite": "juventudtorremolinos.club",
            "strFacebook": "www.facebook.com\/juventuddetorremolinos\/",
            "strTwitter": "twitter.com\/jtorremolinoscf",
            "strInstagram": "www.instagram.com\/juventudtorremolinos.cf",
            "strDescriptionEN": "Juventud de Torremolinos Club de Fútbol is a Spanish football team based in Torremolinos, Málaga, in the autonomous community of Andalusia. Founded in 1958, it plays in Tercera División – Group 9, holding home matches at Estadio Municipal El Pozuelo.",
            "strDescriptionDE": null,
            "strDescriptionFR": null,
            "strDescriptionCN": null,
            "strDescriptionIT": null,
            "strDescriptionJP": null,
            "strDescriptionRU": null,
            "strDescriptionES": null,
            "strDescriptionPT": null,
            "strDescriptionSE": null,
            "strDescriptionNL": null,
            "strDescriptionHU": null,
            "strDescriptionNO": null,
            "strDescriptionIL": null,
            "strDescriptionPL": null,
            "strColour1": "",
            "strColour2": "",
            "strColour3": "",
            "strGender": "Male",
            "strCountry": "Spain",
            "strBadge": "https:\/\/r2.thesportsdb.com\/images\/media\/team\/badge\/4bh1zt1660660153.png",
            "strLogo": null,
            "strFanart1": null,
            "strFanart2": null,
            "strFanart3": null,
            "strFanart4": null,
            "strBanner": null,
            "strEquipment": null,
            "strYoutube": "",
            "strLocked": "unlocked"
        },
        {
            "idTeam": "147606",
            "idESPN": null,
            "idAPIfootball": "15315",
            "intLoved": null,
            "strTeam": "La Unión Atlético",
            "strTeamAlternate": "",
            "strTeamShort": "",
            "intFormedYear": "2010",
            "strSport": "Soccer",
            "strLeague": "Spanish Segunda RFEF Group 4",
            "idLeague": "5091",
            "strLeague2": "",
            "idLeague2": null,
            "strLeague3": "",
            "idLeague3": null,
            "strLeague4": "",
            "idLeague4": null,
            "strLeague5": "",
            "idLeague5": null,
            "strLeague6": "",
            "idLeague6": null,
            "strLeague7": "",
            "idLeague7": null,
            "strDivision": null,
            "idVenue": "16992",
            "strStadium": "Municipal",
            "strKeywords": "",
            "strRSS": "",
            "strLocation": "La Unión, Spain",
            "intStadiumCapacity": "2000",
            "strWebsite": "fclaunionatl.es\/      ",
            "strFacebook": "www.facebook.com\/fclaunionatletico\/",
            "strTwitter": "twitter.com\/fclaunionatl",
            "strInstagram": "www.instagram.com\/fclaunionatletico",
            "strDescriptionEN": "Fútbol Club La Unión Atlético is a Spanish football team based in La Unión, Murcia, in the Region of Murcia. Founded in 2010 as FC Pinatar Arena, it plays in Tercera División – Group 13, holding home matches at Municipal.",
            "strDescriptionDE": null,
            "strDescriptionFR": null,
            "strDescriptionCN": null,
            "strDescriptionIT": null,
            "strDescriptionJP": null,
            "strDescriptionRU": null,
            "strDescriptionES": null,
            "strDescriptionPT": null,
            "strDescriptionSE": null,
            "strDescriptionNL": null,
            "strDescriptionHU": null,
            "strDescriptionNO": null,
            "strDescriptionIL": null,
            "strDescriptionPL": null,
            "strColour1": "",
            "strColour2": "",
            "strColour3": "",
            "strGender": "Male",
            "strCountry": "Spain",
            "strBadge": "https:\/\/r2.thesportsdb.com\/images\/media\/team\/badge\/2cnb5w1710994318.png",
            "strLogo": null,
            "strFanart1": null,
            "strFanart2": null,
            "strFanart3": null,
            "strFanart4": null,
            "strBanner": null,
            "strEquipment": null,
            "strYoutube": "",
            "strLocked": "unlocked"
        },
        {
            "idTeam": "140501",
            "idESPN": null,
            "idAPIfootball": "9398",
            "intLoved": null,
            "strTeam": "Linares Deportivo",
            "strTeamAlternate": "Linares Dep.",
            "strTeamShort": "",
            "intFormedYear": "2009",
            "strSport": "Soccer",
            "strLeague": "Spanish Segunda RFEF Group 4",
            "idLeague": "5091",
            "strLeague2": "",
            "idLeague2": null,
            "strLeague3": "",
            "idLeague3": null,
            "strLeague4": "",
            "idLeague4": null,
            "strLeague5": "",
            "idLeague5": null,
            "strLeague6": "",
            "idLeague6": null,
            "strLeague7": "",
            "idLeague7": null,
            "strDivision": null,
            "idVenue": "0",
            "strStadium": "Linarejos",
            "strKeywords": "Azulillos (Little Blues)",
            "strRSS": "",
            "strLocation": "Linares, Spain",
            "intStadiumCapacity": "10000",
            "strWebsite": "www.linaresdeportivo.es",
            "strFacebook": "",
            "strTwitter": "",
            "strInstagram": "",
            "strDescriptionEN": "Linares Deportivo is a Spanish football team based in Linares, Jaén, in the autonomous community of Andalusia. Founded in 2009 as a replacement for dissolved CD Linares, it plays in Segunda División B – Group 4. The team's stadium is Estadio de Linarejos, with a capacity of 10,000 seats.",
            "strDescriptionDE": null,
            "strDescriptionFR": null,
            "strDescriptionCN": null,
            "strDescriptionIT": null,
            "strDescriptionJP": null,
            "strDescriptionRU": null,
            "strDescriptionES": null,
            "strDescriptionPT": null,
            "strDescriptionSE": null,
            "strDescriptionNL": null,
            "strDescriptionHU": null,
            "strDescriptionNO": null,
            "strDescriptionIL": null,
            "strDescriptionPL": null,
            "strColour1": "",
            "strColour2": "",
            "strColour3": "",
            "strGender": "Male",
            "strCountry": "Spain",
            "strBadge": "https:\/\/r2.thesportsdb.com\/images\/media\/team\/badge\/d0r5pf1609532341.png",
            "strLogo": null,
            "strFanart1": null,
            "strFanart2": null,
            "strFanart3": null,
            "strFanart4": null,
            "strBanner": null,
            "strEquipment": null,
            "strYoutube": "",
            "strLocked": "unlocked"
        },
        {
            "idTeam": "138288",
            "idESPN": null,
            "idAPIfootball": "9596",
            "intLoved": null,
            "strTeam": "Linense",
            "strTeamAlternate": "RB Linense",
            "strTeamShort": null,
            "intFormedYear": "1912",
            "strSport": "Soccer",
            "strLeague": "Spanish Segunda RFEF Group 4",
            "idLeague": "5091",
            "strLeague2": "",
            "idLeague2": null,
            "strLeague3": "",
            "idLeague3": null,
            "strLeague4": "",
            "idLeague4": null,
            "strLeague5": "",
            "idLeague5": null,
            "strLeague6": "",
            "idLeague6": null,
            "strLeague7": "",
            "idLeague7": null,
            "strDivision": null,
            "idVenue": null,
            "strStadium": "Municipal La Línea",
            "strKeywords": "",
            "strRSS": "",
            "strLocation": "La Línea, Spain",
            "intStadiumCapacity": "16120",
            "strWebsite": "",
            "strFacebook": "",
            "strTwitter": "",
            "strInstagram": "",
            "strDescriptionEN": "Real Balompédica Linense is a Spanish football team based in La Línea de la Concepción, in the autonomous community of Andalusia. Founded in 1912 it plays in Segunda División B – Group 4, holding home matches at Estadio Municipal de La Línea de la Concepción, with a capacity of 16,120 seats.",
            "strDescriptionDE": null,
            "strDescriptionFR": null,
            "strDescriptionCN": null,
            "strDescriptionIT": null,
            "strDescriptionJP": null,
            "strDescriptionRU": null,
            "strDescriptionES": null,
            "strDescriptionPT": null,
            "strDescriptionSE": null,
            "strDescriptionNL": null,
            "strDescriptionHU": null,
            "strDescriptionNO": null,
            "strDescriptionIL": null,
            "strDescriptionPL": null,
            "strColour1": "",
            "strColour2": "",
            "strColour3": "",
            "strGender": "Male",
            "strCountry": "Spain",
            "strBadge": "https:\/\/r2.thesportsdb.com\/images\/media\/team\/badge\/qjprzq1656017016.png",
            "strLogo": null,
            "strFanart1": null,
            "strFanart2": null,
            "strFanart3": null,
            "strFanart4": null,
            "strBanner": null,
            "strEquipment": null,
            "strYoutube": "",
            "strLocked": "unlocked"
        },
        {
            "idTeam": "137755",
            "idESPN": null,
            "idAPIfootball": "9404",
            "intLoved": null,
            "strTeam": "Orihuela",
            "strTeamAlternate": "Orihuela Club de Fútbol, Orihuela CF",
            "strTeamShort": "",
            "intFormedYear": "1993",
            "strSport": "Soccer",
            "strLeague": "Spanish Segunda RFEF Group 4",
            "idLeague": "5091",
            "strLeague2": "Copa del Rey",
            "idLeague2": "4483",
            "strLeague3": "",
            "idLeague3": null,
            "strLeague4": "",
            "idLeague4": null,
            "strLeague5": "",
            "idLeague5": null,
            "strLeague6": "",
            "idLeague6": null,
            "strLeague7": "",
            "idLeague7": null,
            "strDivision": null,
            "idVenue": null,
            "strStadium": "Los Arcos",
            "strKeywords": "",
            "strRSS": "",
            "strLocation": "Orihuela, Spain",
            "intStadiumCapacity": "6000",
            "strWebsite": "www.orihuelaclubdefutbol.com",
            "strFacebook": "www.facebook.com\/OrihuelaCF\/",
            "strTwitter": "twitter.com\/Orihuela_CF",
            "strInstagram": "www.instagram.com\/orihuela_cf\/?hl=es",
            "strDescriptionEN": "Orihuela Club de Fútbol is a Spanish football team based in Orihuela, in the Valencian Community. Founded in 1993 it plays in Segunda División B – Group 3, holding home games at Estadio Municipal Los Arcos, with a capacity of 6,000 seats.",
            "strDescriptionDE": null,
            "strDescriptionFR": null,
            "strDescriptionCN": null,
            "strDescriptionIT": null,
            "strDescriptionJP": null,
            "strDescriptionRU": null,
            "strDescriptionES": null,
            "strDescriptionPT": null,
            "strDescriptionSE": null,
            "strDescriptionNL": null,
            "strDescriptionHU": null,
            "strDescriptionNO": null,
            "strDescriptionIL": null,
            "strDescriptionPL": null,
            "strColour1": "",
            "strColour2": "",
            "strColour3": "",
            "strGender": "Male",
            "strCountry": "Spain",
            "strBadge": "https:\/\/r2.thesportsdb.com\/images\/media\/team\/badge\/yx562i1578744097.png",
            "strLogo": null,
            "strFanart1": null,
            "strFanart2": null,
            "strFanart3": null,
            "strFanart4": null,
            "strBanner": null,
            "strEquipment": null,
            "strYoutube": "www.youtube.com\/channel\/UCyELqJQs1_Kspe-SjmR-h6A",
            "strLocked": "unlocked"
        },
        {
            "idTeam": "138308",
            "idESPN": null,
            "idAPIfootball": "9599",
            "intLoved": null,
            "strTeam": "Recreativo Granada",
            "strTeamAlternate": "Granada II, Club Recreativo Granada",
            "strTeamShort": "",
            "intFormedYear": "1947",
            "strSport": "Soccer",
            "strLeague": "Spanish Segunda RFEF Group 4",
            "idLeague": "5091",
            "strLeague2": "",
            "idLeague2": null,
            "strLeague3": "",
            "idLeague3": null,
            "strLeague4": "",
            "idLeague4": null,
            "strLeague5": "",
            "idLeague5": null,
            "strLeague6": "",
            "idLeague6": null,
            "strLeague7": "",
            "idLeague7": null,
            "strDivision": null,
            "idVenue": "20028",
            "strStadium": "Ciudad Deportiva del Granada CF",
            "strKeywords": "",
            "strRSS": "",
            "strLocation": "Granada, Spain",
            "intStadiumCapacity": "2000",
            "strWebsite": "www.granadacf.es",
            "strFacebook": "",
            "strTwitter": "",
            "strInstagram": "",
            "strDescriptionEN": "Club Recreativo Granada is a Spanish football team based in Granada, in the autonomous community of Andalusia. Founded in 1947, it is the reserve team of Granada CF and currently plays in Segunda División B – Group 4, holding home games at Estadio Miguel Prieto, with a capacity for 2,500 spectators.\r\n\r\nUnlike the English League, reserve teams in Spain play in the same football pyramid as their senior team, rather than a separate league. However, reserve teams cannot play in the same division as the main squad.\r\n\r\nReserve teams are also no longer permitted to enter the Copa del Rey. Additionally, only under-23 players or under-25 players with a professional contract can switch between senior and reserve teams.",
            "strDescriptionDE": null,
            "strDescriptionFR": null,
            "strDescriptionCN": null,
            "strDescriptionIT": null,
            "strDescriptionJP": null,
            "strDescriptionRU": null,
            "strDescriptionES": null,
            "strDescriptionPT": null,
            "strDescriptionSE": null,
            "strDescriptionNL": null,
            "strDescriptionHU": null,
            "strDescriptionNO": null,
            "strDescriptionIL": null,
            "strDescriptionPL": null,
            "strColour1": "",
            "strColour2": "",
            "strColour3": "",
            "strGender": "Male",
            "strCountry": "Spain",
            "strBadge": "https:\/\/r2.thesportsdb.com\/images\/media\/team\/badge\/n8ruqz1677473028.png",
            "strLogo": null,
            "strFanart1": null,
            "strFanart2": null,
            "strFanart3": null,
            "strFanart4": null,
            "strBanner": null,
            "strEquipment": null,
            "strYoutube": "",
            "strLocked": "unlocked"
        },
        {
            "idTeam": "138301",
            "idESPN": null,
            "idAPIfootball": "9600",
            "intLoved": null,
            "strTeam": "San Fernando CD",
            "strTeamAlternate": "San Fernando CD",
            "strTeamShort": "",
            "intFormedYear": "2009",
            "strSport": "Soccer",
            "strLeague": "Spanish Segunda RFEF Group 4",
            "idLeague": "5091",
            "strLeague2": "",
            "idLeague2": null,
            "strLeague3": "",
            "idLeague3": null,
            "strLeague4": "",
            "idLeague4": null,
            "strLeague5": "",
            "idLeague5": null,
            "strLeague6": "",
            "idLeague6": null,
            "strLeague7": "",
            "idLeague7": null,
            "strDivision": null,
            "idVenue": "0",
            "strStadium": "Bahía Sur",
            "strKeywords": "",
            "strRSS": "",
            "strLocation": "San Fernando, Spain",
            "intStadiumCapacity": "8000",
            "strWebsite": "sanfernandocd.com",
            "strFacebook": "www.facebook.com\/sanfernandocd\/",
            "strTwitter": "twitter.com\/SanFernando_CD",
            "strInstagram": "www.instagram.com\/sanfernando_cd",
            "strDescriptionEN": "San Fernando Club Deportivo Isleño is a Spanish football team based in San Fernando, Cádiz, in the autonomous community of Andalusia. Founded in 2009 it plays in Segunda División B – Group 4, holding home matches at Estadio Bahía Sur, with a capacity of 8,000 seats.",
            "strDescriptionDE": null,
            "strDescriptionFR": null,
            "strDescriptionCN": null,
            "strDescriptionIT": null,
            "strDescriptionJP": null,
            "strDescriptionRU": null,
            "strDescriptionES": null,
            "strDescriptionPT": null,
            "strDescriptionSE": null,
            "strDescriptionNL": null,
            "strDescriptionHU": null,
            "strDescriptionNO": null,
            "strDescriptionIL": null,
            "strDescriptionPL": null,
            "strColour1": "",
            "strColour2": "",
            "strColour3": "",
            "strGender": "Male",
            "strCountry": "Spain",
            "strBadge": "https:\/\/r2.thesportsdb.com\/images\/media\/team\/badge\/110w8d1579987844.png",
            "strLogo": null,
            "strFanart1": null,
            "strFanart2": null,
            "strFanart3": null,
            "strFanart4": null,
            "strBanner": null,
            "strEquipment": null,
            "strYoutube": "www.youtube.com\/channel\/UCboXpDPVblLWIJPZXXo01Kg",
            "strLocked": "unlocked"
        },
        {
            "idTeam": "135679",
            "idESPN": null,
            "idAPIfootball": "800",
            "intLoved": null,
            "strTeam": "UCAM Murcia",
            "strTeamAlternate": "UCAM",
            "strTeamShort": "",
            "intFormedYear": "1999",
            "strSport": "Soccer",
            "strLeague": "Spanish Segunda RFEF Group 4",
            "idLeague": "5091",
            "strLeague2": "",
            "idLeague2": null,
            "strLeague3": "",
            "idLeague3": null,
            "strLeague4": "",
            "idLeague4": null,
            "strLeague5": "",
            "idLeague5": null,
            "strLeague6": "",
            "idLeague6": null,
            "strLeague7": "",
            "idLeague7": null,
            "strDivision": null,
            "idVenue": "0",
            "strStadium": "La Condomina",
            "strKeywords": "",
            "strRSS": "",
            "strLocation": "Múrcia",
            "intStadiumCapacity": "16000",
            "strWebsite": "www.ucamdeportes.com\/ucamcf",
            "strFacebook": "www.facebook.com\/UCAMMurciaCF",
            "strTwitter": "twitter.com\/ucammurciacf",
            "strInstagram": "instagram.com\/ucammurcia_cf",
            "strDescriptionEN": "Universidad Católica de Murcia Club de Fútbol is a Spanish football club based in Murcia. Founded in 1999 it plays in Segunda División, holding home games at Estadio de La Condomina, with a capacity of 16,800 spectators.",
            "strDescriptionDE": null,
            "strDescriptionFR": null,
            "strDescriptionCN": null,
            "strDescriptionIT": null,
            "strDescriptionJP": null,
            "strDescriptionRU": null,
            "strDescriptionES": "El Universidad Católica de Murcia Club de Fútbol, más conocido como UCAM Murcia Club de Fútbol, es un club de fútbol de España de la localidad de Murcia, que juega como local en el Estadio de La Condomina. Pertenece a la Universidad Católica San Antonio. Fue fundado en 1999 y desde su creación ha participado en el Grupo XIII de la Tercera División de España hasta la temporada 2011\/2012 que lo hace en la Segunda División B cuando la UCAM se hace con el club y compra una plaza en ésta categoría con el objetivo de aprovechar sinergias con las demás matrices corporativas de la UCAM para maximizar los beneficios de la Universidad privada de Murcia. Tras estar muy cerca de lograr la permanencia, el equipo regresa en la temporada 2013\/2014 al Grupo XIII de la Tercera División de España. El 7 de mayo de 2016 se proclamó campeón del grupo IV de la Segunda División B, ascendiendo a la Segunda División de España el 30 de mayo de ese mismo año después de derrotar al Real Madrid Castilla Club de Fútbol.",
            "strDescriptionPT": null,
            "strDescriptionSE": null,
            "strDescriptionNL": null,
            "strDescriptionHU": null,
            "strDescriptionNO": null,
            "strDescriptionIL": null,
            "strDescriptionPL": null,
            "strColour1": "",
            "strColour2": "",
            "strColour3": "",
            "strGender": "Male",
            "strCountry": "Spain",
            "strBadge": "https:\/\/r2.thesportsdb.com\/images\/media\/team\/badge\/vuuwwp1471878623.png",
            "strLogo": "https:\/\/r2.thesportsdb.com\/images\/media\/team\/logo\/stquxy1471879043.png",
            "strFanart1": null,
            "strFanart2": null,
            "strFanart3": null,
            "strFanart4": null,
            "strBanner": null,
            "strEquipment": "https:\/\/r2.thesportsdb.com\/images\/media\/team\/equipment\/wqssqq1471878891.png",
            "strYoutube": "www.youtube.com\/channel\/UCMISGhv_CUaY6pNKQcu00PQ",
            "strLocked": "unlocked"
        },
        {
            "idTeam": "140507",
            "idESPN": null,
            "idAPIfootball": "5282",
            "intLoved": null,
            "strTeam": "Villanovense",
            "strTeamAlternate": "",
            "strTeamShort": "",
            "intFormedYear": "1992",
            "strSport": "Soccer",
            "strLeague": "Spanish Segunda RFEF Group 4",
            "idLeague": "5091",
            "strLeague2": "",
            "idLeague2": null,
            "strLeague3": "",
            "idLeague3": null,
            "strLeague4": "",
            "idLeague4": null,
            "strLeague5": "",
            "idLeague5": null,
            "strLeague6": "",
            "idLeague6": null,
            "strLeague7": "",
            "idLeague7": null,
            "strDivision": null,
            "idVenue": "0",
            "strStadium": "Romero Cuerda",
            "strKeywords": "",
            "strRSS": "",
            "strLocation": "Villanueva de la Serena, Spain",
            "intStadiumCapacity": "5000",
            "strWebsite": "villanovense.es\/web20",
            "strFacebook": "",
            "strTwitter": "",
            "strInstagram": "",
            "strDescriptionEN": "Club de Fútbol Villanovense is a Spanish football team based in Villanueva de la Serena, in the autonomous community of Extremadura. Founded in 1992 it plays in Segunda División B – Group 4, holding home matches at Estadio Romero Cuerda, with a capacity of 5,000 seats.",
            "strDescriptionDE": null,
            "strDescriptionFR": null,
            "strDescriptionCN": null,
            "strDescriptionIT": null,
            "strDescriptionJP": null,
            "strDescriptionRU": null,
            "strDescriptionES": null,
            "strDescriptionPT": null,
            "strDescriptionSE": null,
            "strDescriptionNL": null,
            "strDescriptionHU": null,
            "strDescriptionNO": null,
            "strDescriptionIL": null,
            "strDescriptionPL": null,
            "strColour1": "",
            "strColour2": "",
            "strColour3": "",
            "strGender": "Male",
            "strCountry": "Spain",
            "strBadge": "https:\/\/r2.thesportsdb.com\/images\/media\/team\/badge\/6nvtys1690612451.png",
            "strLogo": null,
            "strFanart1": null,
            "strFanart2": null,
            "strFanart3": null,
            "strFanart4": null,
            "strBanner": null,
            "strEquipment": null,
            "strYoutube": "",
            "strLocked": "unlocked"
        },
        {
            "idTeam": "133842",
            "idESPN": null,
            "idAPIfootball": "9770",
            "intLoved": null,
            "strTeam": "Xerez",
            "strTeamAlternate": "",
            "strTeamShort": "",
            "intFormedYear": "1947",
            "strSport": "Soccer",
            "strLeague": "Spanish Segunda RFEF Group 4",
            "idLeague": "5091",
            "strLeague2": "Copa del Rey",
            "idLeague2": "4483",
            "strLeague3": "",
            "idLeague3": null,
            "strLeague4": "",
            "idLeague4": null,
            "strLeague5": "",
            "idLeague5": null,
            "strLeague6": "",
            "idLeague6": null,
            "strLeague7": "",
            "idLeague7": null,
            "strDivision": null,
            "idVenue": "0",
            "strStadium": "Chapín",
            "strKeywords": "",
            "strRSS": "",
            "strLocation": "Chapín, Jerez, Andalusia, Spain",
            "intStadiumCapacity": "20523",
            "strWebsite": "www.xerezcd.com",
            "strFacebook": "",
            "strTwitter": "",
            "strInstagram": "",
            "strDescriptionEN": "Xerez Club Deportivo, known simply as Xerez, is a Spanish football team based in Jerez de la Frontera, in the autonomous community of Andalusia. Founded on 24 September 1947 it plays in Primera Andaluza, holding home matches at Estadio Municipal de Chapín, with an overall 20,742-seat capacity.\r\n\r\nTeam colours are usually blue shirt and socks, and white shorts.\r\n\r\nDue to the link between Jerez de la Frontera and the United Kingdom created by the exports of sherry (Jerez in Spanish), football had its beginnings in the region towards the second half of the 19th century. In the early 20th century Sir Thomas Spencer, who worked with the William & Humbert winery, founded Sociedad Jerez Foot-Ball Club – he also served as chairman, player and captain.\r\n\r\nFrom 1942 to 1947 the club had several names, ending with Jerez Club Deportivo, which was changed to the current name in 1960s. Xerez first reached the second division in 1953–54, remaining there for five years; previously, in the 1940s, the team had promoted on the field but, due to the \"high national interest\" of the dictatorial government, left its position to España de Tánger.\r\n\r\nThe team's new stadium, Estadio Municipal de Chapín, was inaugurated on 10 July 1988, replacing the old Estadio Domecq – the first match there was a friendly against Real Madrid. After decades in that category and also in the third, it had a 2001–02 second level campaign which almost resulted in an historic La Liga promotion, only one year after doing the same thing; the club seemed certain to gain promotion all season, but ultimately failed after a dramatic loss of form towards its closure, only gaining four points in the last eight matches.\r\n\r\nSince then, Xerez finished in the top 10 in division two each campaign, except in the 2007–08 season when a weak start led to a 15th-place finish. The following campaign proved excellent, as the club was always in the top positions: on 13 June 2009, after beating SD Huesca 2–1 at home, it achieved promotion to the top division for the first time in its history. In the final day of the competition, a draw at Celta de Vigo proved enough for the title, as CD Tenerife lost 1–2 home to CD Castellón in the final minute.\r\n\r\nThe first season of Xerez in the top flight would be short-lived, as it ended in relegation. After only collecting seven points from the first 19 games – which led to the sacking of coach José Ángel Ziganda – the club amassed 27 in the remaining 19 with Néstor Gorosito as boss, not good enough however to prevent the drop as last (the club, however, had chances to stay up until the final round, a 1–1 draw at CA Osasuna).\r\n\r\nXerez ranked eighth and 14th in the two following second level seasons, respectively. The 2012–13 campaign, however, was disastrous on all levels, as the team finished in 22nd and last position as a direct consequence of enduring serious financial difficulties for several years, and the situation culminated with the club being relegated to the fourth division on 1 August.\r\n\r\nAfter the Xerez's season, a bunch of supporters founded a new club in the lower leagues, named Xerez Deportivo FC due to the club's institutional problems. While the latter was promoted to Primera Provincial, the former was again relegated, this time to Primera Andaluza, until May 2017, when Xerez came back to Tercera División.",
            "strDescriptionDE": null,
            "strDescriptionFR": null,
            "strDescriptionCN": null,
            "strDescriptionIT": null,
            "strDescriptionJP": null,
            "strDescriptionRU": null,
            "strDescriptionES": null,
            "strDescriptionPT": null,
            "strDescriptionSE": null,
            "strDescriptionNL": null,
            "strDescriptionHU": null,
            "strDescriptionNO": null,
            "strDescriptionIL": null,
            "strDescriptionPL": null,
            "strColour1": "",
            "strColour2": "",
            "strColour3": "",
            "strGender": "Male",
            "strCountry": "Spain",
            "strBadge": "https:\/\/r2.thesportsdb.com\/images\/media\/team\/badge\/cxpzkp1511516976.png",
            "strLogo": null,
            "strFanart1": null,
            "strFanart2": null,
            "strFanart3": null,
            "strFanart4": null,
            "strBanner": null,
            "strEquipment": null,
            "strYoutube": "",
            "strLocked": "unlocked"
        },
        {
            "idTeam": "144239",
            "idESPN": null,
            "idAPIfootball": "9771",
            "intLoved": null,
            "strTeam": "Xerez Deportivo",
            "strTeamAlternate": "",
            "strTeamShort": "",
            "intFormedYear": "2013",
            "strSport": "Soccer",
            "strLeague": "Spanish Segunda RFEF Group 4",
            "idLeague": "5091",
            "strLeague2": "",
            "idLeague2": null,
            "strLeague3": "",
            "idLeague3": null,
            "strLeague4": "",
            "idLeague4": null,
            "strLeague5": "",
            "idLeague5": null,
            "strLeague6": "",
            "idLeague6": null,
            "strLeague7": "",
            "idLeague7": null,
            "strDivision": null,
            "idVenue": "0",
            "strStadium": "Chapín",
            "strKeywords": "",
            "strRSS": "",
            "strLocation": "Jerez de la Frontera",
            "intStadiumCapacity": "20523",
            "strWebsite": "",
            "strFacebook": "",
            "strTwitter": "",
            "strInstagram": "",
            "strDescriptionEN": "Xerez Deportivo Fútbol Club, also known as Xerez DFC, is a football club in Jerez de la Frontera. It was founded in 2013 by a group of fans due to the critical situation of Xerez CD. It plays in the Segunda División RFEF – Group 4, holding home matches at the Estadio Municipal de Chapín, with an overall 20,523-seat capacity. The team colours are usually blue shirts and socks, with white shorts.",
            "strDescriptionDE": null,
            "strDescriptionFR": null,
            "strDescriptionCN": null,
            "strDescriptionIT": null,
            "strDescriptionJP": null,
            "strDescriptionRU": null,
            "strDescriptionES": null,
            "strDescriptionPT": null,
            "strDescriptionSE": null,
            "strDescriptionNL": null,
            "strDescriptionHU": null,
            "strDescriptionNO": null,
            "strDescriptionIL": null,
            "strDescriptionPL": null,
            "strColour1": "",
            "strColour2": "",
            "strColour3": "",
            "strGender": "Male",
            "strCountry": "Spain",
            "strBadge": "https:\/\/r2.thesportsdb.com\/images\/media\/team\/badge\/wxj6vr1637628167.png",
            "strLogo": null,
            "strFanart1": null,
            "strFanart2": null,
            "strFanart3": null,
            "strFanart4": null,
            "strBanner": null,
            "strEquipment": null,
            "strYoutube": "",
            "strLocked": "unlocked"
        }
    ]
}